dsplayer_lyrics/__init__.py
dsplayer_lyrics/lyrics.py
dsplayer_lyrics-1.0.0.dist-info/LICENSE
dsplayer_lyrics-1.0.0.dist-info/METADATA
dsplayer_lyrics-1.0.0.dist-info/WHEEL
dsplayer_lyrics-1.0.0.dist-info/entry_points.txt
dsplayer_lyrics-1.0.0.dist-info/top_level.txt
dsplayer_lyrics-1.0.0.dist-info/RECORD
